simpleconfig/__init__.py
simpleconfig/configuration.py
simpleconfig/exceptions.py
simpleconfig/settings.py
simpleconfig/formatters/__init__.py
simpleconfig/formatters/exceptions.py
simpleconfig/formatters/format_factory.py
simpleconfig/formatters/formatbase.py
simpleconfig/formatters/ini_formatter.py
simpleconfig/formatters/json_formatter.py
pysimpleconfig-0.1.6.dist-info/LICENSE
pysimpleconfig-0.1.6.dist-info/METADATA
pysimpleconfig-0.1.6.dist-info/WHEEL
pysimpleconfig-0.1.6.dist-info/top_level.txt
pysimpleconfig-0.1.6.dist-info/RECORD
